wfctl/__init__.py
wfctl/help.py
wfctl/ipc.py
wfctl/main.py
wfctl/utils.py
wfctl-0.8.8.dist-info/licenses/LICENSE
wfctl-0.8.8.dist-info/METADATA
wfctl-0.8.8.dist-info/WHEEL
wfctl-0.8.8.dist-info/entry_points.txt
wfctl-0.8.8.dist-info/top_level.txt
wfctl-0.8.8.dist-info/RECORD
