Metadata-Version: 2.4
Name: wfctl
Version: 0.8.8
Summary: A command-line tool for interacting with Wayfire.
Home-page: https://github.com/killown/wfctl
Author: killown
Author-email: systemofdown@gmail.com
License-File: LICENSE
Requires-Dist: wayfire
Dynamic: author
Dynamic: author-email
Dynamic: description
Dynamic: description-content-type
Dynamic: home-page
Dynamic: license-file
Dynamic: requires-dist
Dynamic: summary
